<Properties StartupConfiguration="{723884EE-3AD6-471C-B3CD-72A76DA6C762}|Default">
  <MonoDevelop.Ide.Workbench ActiveDocument="FinalProjectWorkspace/Program.cs">
    <Files>
      <File FileName="FinalProjectWorkspace/Models/MovieReview.cs" Line="19" Column="25" />
      <File FileName="FinalProjectWorkspace/Controllers/MovieReviewController.cs" Line="89" Column="45" />
      <File FileName="FinalProjectWorkspace/Views/MovieReview/Create.cshtml" />
      <File FileName="FinalProjectWorkspace/Views/MovieReview/Edit.cshtml" />
      <File FileName="FinalProjectWorkspace/Models/Ticket.cs" />
      <File FileName="FinalProjectWorkspace/Models/Order.cs" />
      <File FileName="FinalProjectWorkspace/Views/MovieReview/Index.cshtml" />
      <File FileName="FinalProjectWorkspace/Views/MovieReview/Details.cshtml" />
      <File FileName="FinalProjectWorkspace/Views/Movie/SearchResults.cshtml" />
      <File FileName="FinalProjectWorkspace/Controllers/MovieController.cs" />
      <File FileName="FinalProjectWorkspace/Views/Home/Index.cshtml" />
      <File FileName="FinalProjectWorkspace/Models/Movie.cs" />
      <File FileName="FinalProjectWorkspace/Models/Showing.cs" />
      <File FileName="FinalProjectWorkspace/Models/AppUser.cs" />
      <File FileName="FinalProjectWorkspace/Views/Order/Details.cshtml" Line="1" Column="1" />
      <File FileName="FinalProjectWorkspace/Program.cs" Line="16" Column="1" />
    </Files>
    <Pads>
      <Pad Id="ProjectPad">
        <State name="__root__">
          <Option id="ShowAllFiles" value="True" />
          <Node name="FinalProjectWorkspace" expanded="True">
            <Node name="FinalProjectWorkspace" expanded="True">
              <Node name="Controllers" expanded="True" />
              <Node name="DAL" expanded="True" />
              <Node name="Models" expanded="True">
                <Node name="ViewModels" expanded="True" />
              </Node>
              <Node name="Views" expanded="True">
                <Node name="Account" expanded="True" />
                <Node name="Home" expanded="True" />
                <Node name="Movie" expanded="True" />
                <Node name="MovieReview" expanded="True" />
                <Node name="Order" expanded="True" />
                <Node name="RoleAdmin" expanded="True" />
                <Node name="Seed" expanded="True" />
                <Node name="Shared" expanded="True" />
              </Node>
              <Node name="Program.cs" selected="True" />
            </Node>
          </Node>
        </State>
      </Pad>
    </Pads>
  </MonoDevelop.Ide.Workbench>
  <MonoDevelop.Ide.DebuggingService.PinnedWatches />
  <MonoDevelop.Ide.ItemProperties.FinalProjectWorkspace PreferredExecutionTarget="/Applications/Google Chrome.app" />
  <MonoDevelop.Ide.Workspace ActiveConfiguration="Debug" />
  <MonoDevelop.Ide.DebuggingService.Breakpoints>
    <BreakpointStore />
  </MonoDevelop.Ide.DebuggingService.Breakpoints>
  <MultiItemStartupConfigurations />
</Properties>